{
  "id": "4a9ad08c-1dc6-4afb-9d3c-fefeaf1c13ea",
  "name": "field-view-json",
  "type": "cccccccc-0000-0000-0000-000000000000",
  "created": 1769279958720,
  "modified": 1770144885829,
  "content": {
    "description": "JSON fallback field",
    "code": "\nexport function render(value, options, api) {\n  const { mode, onChange, label } = options;\n  const wrapper = api.createElement('div', { className: 'field-json' });\n  wrapper.style.cssText = 'display: flex; flex-direction: column; gap: 4px;';\n\n  if (label) {\n    const labelEl = api.createElement('label');\n    labelEl.textContent = label;\n    labelEl.style.cssText = 'font-weight: 500; font-size: 14px; color: var(--color-text);';\n    wrapper.appendChild(labelEl);\n  }\n\n  const jsonStr = JSON.stringify(value, null, 2);\n\n  if (mode === 'editable' && onChange) {\n    const textarea = api.createElement('textarea', { style: 'padding: 8px; border: 1px solid var(--color-border); border-radius: var(--border-radius); font-size: 13px; font-family: monospace; resize: vertical; min-height: 100px;' });\n    textarea.value = jsonStr;\n    const errorEl = api.createElement('div');\n    errorEl.style.cssText = 'color: var(--color-danger); font-size: 12px; min-height: 16px;';\n    textarea.oninput = (e) => {\n      try {\n        onChange(JSON.parse(e.target.value));\n        errorEl.textContent = '';\n        textarea.style.borderColor = 'var(--color-border)';\n      } catch (err) {\n        errorEl.textContent = 'Invalid JSON';\n        textarea.style.borderColor = 'var(--color-danger)';\n      }\n    };\n    wrapper.appendChild(textarea);\n    wrapper.appendChild(errorEl);\n  } else {\n    const pre = api.createElement('pre');\n    pre.textContent = jsonStr;\n    pre.style.cssText = 'padding: 8px; background: var(--color-bg-surface-alt); border-radius: var(--border-radius); font-size: 13px; font-family: monospace; white-space: pre-wrap; margin: 0;';\n    wrapper.appendChild(pre);\n  }\n  return wrapper;\n}\n",
    "_symbols": {
      "render": {
        "name": "render",
        "line": 2,
        "col": 7,
        "endLine": 40,
        "endCol": 1,
        "kind": "function",
        "scope": null
      },
      "render.wrapper": {
        "name": "wrapper",
        "line": 4,
        "col": 8,
        "endLine": 4,
        "endCol": 71,
        "kind": "variable",
        "scope": "render"
      },
      "render.labelEl": {
        "name": "labelEl",
        "line": 8,
        "col": 10,
        "endLine": 8,
        "endCol": 46,
        "kind": "variable",
        "scope": "render"
      },
      "render.jsonStr": {
        "name": "jsonStr",
        "line": 14,
        "col": 8,
        "endLine": 14,
        "endCol": 48,
        "kind": "variable",
        "scope": "render"
      },
      "render.textarea": {
        "name": "textarea",
        "line": 17,
        "col": 10,
        "endLine": 17,
        "endCol": 232,
        "kind": "variable",
        "scope": "render"
      },
      "render.errorEl": {
        "name": "errorEl",
        "line": 19,
        "col": 10,
        "endLine": 19,
        "endCol": 44,
        "kind": "variable",
        "scope": "render"
      },
      "render.pre": {
        "name": "pre",
        "line": 34,
        "col": 10,
        "endLine": 34,
        "endCol": 40,
        "kind": "variable",
        "scope": "render"
      }
    }
  },
  "attachments": []
}