{
  "id": "716cc99c-8cb5-4339-a7d6-96c2ff1bc193",
  "name": "Hobson Development",
  "type": "4bbe108c-9db9-430d-a65d-7b5a00831bbb",
  "created": 1768391019605,
  "modified": 1770745096176,
  "content": {
    "description": "",
    "tags": [
      "c0c0c0c0-0060-0000-0000-000000000000"
    ]
  },
  "preferredView": "ef793c27-2d4b-4c99-b05a-2769db5bc5a9",
  "attachments": [
    {
      "id": "c0c0c0c0-0040-0000-0000-000000000000",
      "view": {
        "x": 719,
        "y": 507,
        "z": 12,
        "width": 422,
        "height": 304,
        "anchor": null,
        "minimized": false,
        "maximized": false
      }
    },
    {
      "id": "e62219e1-939f-4955-a427-ce67016b9079",
      "view": {
        "z": 0,
        "anchor": "left",
        "x": 0,
        "y": 0,
        "width": 315,
        "height": 500,
        "minimized": false,
        "maximized": false,
        "pinned": null
      }
    },
    {
      "id": "c0c0c0c0-0036-0000-0000-000000000000",
      "view": {
        "x": 586,
        "y": 85,
        "z": 10,
        "width": 600,
        "height": 500,
        "anchor": null,
        "minimized": false,
        "maximized": false
      }
    },
    {
      "id": "8fd956ff-01f4-48f5-8afb-42fc2718005b",
      "view": {
        "z": 3,
        "x": 0,
        "y": 0,
        "width": 1062,
        "height": 850,
        "anchor": null,
        "minimized": true,
        "maximized": false
      }
    },
    {
      "id": "56a2c83c-1fd4-4db7-a3e8-3aa152524721",
      "view": {
        "z": 13,
        "type": "7e570003-0000-4000-8000-000000000000",
        "innerView": {
          "type": "2ac2dc31-5b49-4731-b53c-47b01adc4de4"
        },
        "minimized": false,
        "maximized": false,
        "x": 449,
        "y": 157,
        "width": 600,
        "height": 500,
        "anchor": null
      },
      "previousView": {
        "z": 5,
        "type": "2ac2dc31-5b49-4731-b53c-47b01adc4de4",
        "innerView": {
          "type": "7e570003-0000-4000-8000-000000000000"
        }
      }
    },
    {
      "id": "99999999-0000-0000-0000-000000000000",
      "view": {
        "z": 25,
        "x": 511,
        "y": 251,
        "width": 600,
        "height": 500,
        "anchor": null,
        "minimized": true,
        "maximized": false
      }
    },
    {
      "id": "ac0ac0ac-0008-0000-0000-000000000000",
      "view": {
        "z": 13,
        "x": 399,
        "y": 0,
        "width": 845,
        "height": 670,
        "anchor": null,
        "minimized": true,
        "maximized": false
      }
    },
    {
      "id": "9eaa5962-a61a-4320-943d-649fd7c4b98b",
      "view": {
        "z": 14
      }
    }
  ],
  "children": [
    {
      "id": "163e1a0a-f1d9-45f9-9490-50a37aa9c259",
      "view": {
        "type": "9428203f-c088-4a54-bbcb-fdbef244189e",
        "x": 0,
        "y": 0,
        "width": 258,
        "height": 934,
        "z": 0,
        "pinned": null,
        "minimized": false,
        "maximized": false,
        "anchor": "left"
      },
      "previousView": {
        "type": "d4e5f6a7-b8c9-4d0e-a1b2-c3d4e5f6a7b8"
      }
    },
    {
      "id": "c3f4c6ad-e827-4999-bf22-724873a5aade",
      "view": {
        "x": 396,
        "y": 9,
        "z": 0,
        "width": 1201,
        "height": 777,
        "anchor": null,
        "type": "ef793c27-2d4b-4c99-b05a-2769db5bc5a9",
        "innerView": {
          "type": "fa8102f6-2b26-4d48-8a7f-79c9ec436e25"
        },
        "minimized": false,
        "maximized": false
      }
    },
    {
      "id": "f1111111-0003-0000-0000-000000000000"
    },
    {
      "id": "43b8f6c8-a575-4610-83a4-fb3c6bd3d5d8",
      "view": {
        "navigateTo": {
          "field": "code",
          "line": 31
        }
      }
    },
    {
      "id": "b429b19d-ef0d-4f4f-b2a2-b9e6f80451f2",
      "view": {
        "navigateTo": {
          "field": "code",
          "line": 188
        },
        "type": null,
        "z": 2
      },
      "previousView": {
        "navigateTo": {
          "field": "code",
          "line": 188
        }
      }
    },
    {
      "id": "ef793c27-2d4b-4c99-b05a-2769db5bc5a9",
      "view": {
        "navigateTo": {
          "field": "code",
          "lines": "1164"
        }
      }
    }
  ]
}