{
  "id": "dafc22a5-13bf-4b42-937d-52f002c4bc70",
  "name": "view-update-watcher",
  "type": "22222222-0000-0000-0000-000000000000",
  "created": 1769620000000,
  "modified": 1775756677360,
  "watches": [
    {
      "event": "e0e00000-0001-0002-0000-000000000000",
      "type": "aaaaaaaa-0000-0000-0000-000000000000"
    }
  ],
  "content": {
    "description": [
      ":doc",
      [
        ":p",
        {
          "s": "Watches for view code changes and re-renders all items using that view."
        }
      ]
    ],
    "code": "// Watches for view code changes and re-renders all items using that view.\n// This ensures that when you edit a view's code, all items currently\n// rendered with that view update immediately.\n\nexport async function onItemUpdated({ id, item }, api) {\n  const vpMgr = await api.require('viewport-manager');\n  const rendering = vpMgr.getRendering();\n  const result = await rendering.rerenderByView(id);\n  if (result.updated > 0) {\n    console.log(`[view-update-watcher] Re-rendered ${result.updated} items using view ${item.name || id}`);\n  }\n}\n",
    "_symbols": {
      "onItemUpdated": {
        "name": "onItemUpdated",
        "line": 5,
        "col": 7,
        "endLine": 12,
        "endCol": 1,
        "kind": "function",
        "scope": null,
        "signature": "({ ... }, api)"
      },
      "onItemUpdated.vpMgr": {
        "name": "vpMgr",
        "line": 6,
        "col": 8,
        "endLine": 6,
        "endCol": 53,
        "kind": "variable",
        "scope": "onItemUpdated"
      },
      "onItemUpdated.rendering": {
        "name": "rendering",
        "line": 7,
        "col": 8,
        "endLine": 7,
        "endCol": 40,
        "kind": "variable",
        "scope": "onItemUpdated"
      },
      "onItemUpdated.result": {
        "name": "result",
        "line": 8,
        "col": 8,
        "endLine": 8,
        "endCol": 51,
        "kind": "variable",
        "scope": "onItemUpdated"
      }
    }
  },
  "attachments": []
}