{
  "id": "fa99b548-f705-45fd-8e31-53f4e0818a66",
  "name": "New Users",
  "type": "4bbe108c-9db9-430d-a65d-7b5a00831bbb",
  "created": 1770817745319,
  "modified": 1773828348360,
  "attachments": [
    {
      "id": "a0a0a0a0-d0c0-4000-8000-000000000005",
      "view": {
        "anchor": "left",
        "x": 0,
        "y": 0,
        "width": 600,
        "height": 500,
        "z": 0,
        "minimized": false,
        "maximized": false,
        "pinned": null,
        "innerView": {
          "type": "d0d0d0d0-0004-0000-0000-000000000000"
        },
        "type": "d0d0d0d0-0006-0000-0000-000000000000"
      },
      "previousView": {
        "anchor": "left",
        "x": 0,
        "y": 0,
        "width": 600,
        "height": 500,
        "z": 0,
        "minimized": false,
        "maximized": false,
        "pinned": null,
        "innerView": {
          "type": "d0d0d0d0-0006-0000-0000-000000000000"
        },
        "type": "d0d0d0d0-0004-0000-0000-000000000000"
      }
    },
    {
      "id": "12e0b897-dfe0-4212-b9c9-7e67ea30da9b",
      "view": {
        "x": 0,
        "y": 0,
        "width": 285,
        "height": null,
        "anchor": "right",
        "z": 0,
        "minimized": false,
        "maximized": false,
        "pinned": null
      }
    },
    {
      "id": "e64adaeb-f701-400a-a3b7-a3cd36eb7b16",
      "view": {
        "x": 140,
        "y": 140,
        "z": 1,
        "width": 600,
        "height": 500,
        "anchor": null,
        "minimized": true,
        "maximized": false
      }
    },
    {
      "id": "d1a00000-0001-0000-0000-000000000000",
      "view": {
        "x": 170,
        "y": 170,
        "z": 1,
        "width": 600,
        "height": 500,
        "anchor": null,
        "minimized": true,
        "maximized": false
      }
    }
  ],
  "content": {
    "tags": [
      "c0c0c0c0-0060-0000-0000-000000000000"
    ]
  }
}